{
  "project_info": {
    "project_number": "605268054562",
    "firebase_url": "https://seniorzyapp.firebaseio.com",
    "project_id": "seniorzyapp",
    "storage_bucket": "seniorzyapp.appspot.com"
  },
  "client": [
    {
      "client_info": {
        "mobilesdk_app_id": "1:605268054562:android:492d5a1346c6666d",
        "android_client_info": {
          "package_name": "com.example.wholoose.seniorzy"
        }
      },
      "oauth_client": [
        {
          "client_id": "605268054562-ihkmpqu5dfp5dc10e6b1ikrqhen54270.apps.googleusercontent.com",
          "client_type": 1,
          "android_info": {
            "package_name": "com.example.wholoose.seniorzy",
            "certificate_hash": "39586984e21d2c6ea4b917c702165488a472f807"
          }
        },
        {
          "client_id": "605268054562-3hc85kimmpeqpv0gd8gdsp320k4vou1h.apps.googleusercontent.com",
          "client_type": 3
        }
      ],
      "api_key": [
        {
          "current_key": "AIzaSyB16YHR1a9B0rxRtQ0N806LPb9oRCMHSCc"
        }
      ],
      "services": {
        "appinvite_service": {
          "other_platform_oauth_client": [
            {
              "client_id": "605268054562-3hc85kimmpeqpv0gd8gdsp320k4vou1h.apps.googleusercontent.com",
              "client_type": 3
            }
          ]
        }
      }
    }
  ],
  "configuration_version": "1"
}